MANIFEST.in
README.rst
setup.py
hyde_zipper.egg-info/PKG-INFO
hyde_zipper.egg-info/SOURCES.txt
hyde_zipper.egg-info/dependency_links.txt
hyde_zipper.egg-info/not-zip-safe
hyde_zipper.egg-info/requires.txt
hyde_zipper.egg-info/top_level.txt
zipper/__init__.py
zipper/site_post_processors.py